iosappinfoparser/__init__.py
iosappinfoparser/info_plist.py
iOSAppInfoParser-1.0.6.dist-info/LICENSE
iOSAppInfoParser-1.0.6.dist-info/METADATA
iOSAppInfoParser-1.0.6.dist-info/WHEEL
iOSAppInfoParser-1.0.6.dist-info/top_level.txt
iOSAppInfoParser-1.0.6.dist-info/RECORD
