Metadata-Version: 2.1
Name: iOSAppInfoParser
Version: 1.0.6
Summary: UNKNOWN
Home-page: https://github.com/shede333/iOSAppInfoParser
Author: shede333
Author-email: 333wshw@163.com
License: UNKNOWN
Keywords: ios app info.plist infoPlist info parser
Platform: UNKNOWN
Classifier: Development Status :: 5 - Production/Stable
Classifier: Natural Language :: Chinese (Simplified)
Classifier: License :: OSI Approved :: MIT License
Classifier: Operating System :: MacOS :: MacOS X
Classifier: Operating System :: POSIX
Classifier: Topic :: Software Development :: Libraries :: Python Modules
Classifier: Programming Language :: Python
Classifier: Programming Language :: Python :: 3
Classifier: Programming Language :: Python :: 3.6
Classifier: Programming Language :: Python :: 3.7
Classifier: Programming Language :: Python :: 3.8
Requires-Python: ~=3.6
Requires-Dist: Pillow (>=7.0)
